LICENSE.txt
MANIFEST.in
po_translate.py
setup.py
version.py
po_translate.egg-info/PKG-INFO
po_translate.egg-info/SOURCES.txt
po_translate.egg-info/dependency_links.txt
po_translate.egg-info/entry_points.txt
po_translate.egg-info/requires.txt
po_translate.egg-info/top_level.txt