Metadata-Version: 1.0
Name: po-translate
Version: 0.1
Summary: A tool for translating .PO files by Google translate API
Home-page: http://bitbucket.org/victorlin/po_translate
Author: Victor Lin
Author-email: bornstub@gmail.com
License: MIT
Platform: UNKNOWN
